paws/__init__.py
paws/paws_config.py
paws/api/__init__.py
paws/core/__init__.py
paws/core/pawstools.py
paws/core/models/DictTree.py
paws/core/models/ListModel.py
paws/core/models/TreeItem.py
paws/core/models/TreeModel.py
paws/core/models/__init__.py
paws/core/operations/OpManager.py
paws/core/operations/Operation.py
paws/core/operations/__init__.py
paws/core/operations/optools.py
paws/core/operations/EXECUTION/__init__.py
paws/core/operations/EXECUTION/BATCH/BatchFromDirectory.py
paws/core/operations/EXECUTION/BATCH/BatchFromFiles.py
paws/core/operations/EXECUTION/BATCH/BatchPostProcess.py
paws/core/operations/EXECUTION/BATCH/__init__.py
paws/core/operations/EXECUTION/REALTIME/RealtimeFromFiles.py
paws/core/operations/EXECUTION/REALTIME/__init__.py
paws/core/operations/IO/BuildFilePath.py
paws/core/operations/IO/ReadPONI.py
paws/core/operations/IO/__init__.py
paws/core/operations/IO/BL15/ReadHeader_SSRL15.py
paws/core/operations/IO/BL15/ReadImageAndHeader_SSRL15.py
paws/core/operations/IO/BL15/__init__.py
paws/core/operations/IO/CALIBRATION/NikaToPONI.py
paws/core/operations/IO/CALIBRATION/ReadPONI.py
paws/core/operations/IO/CALIBRATION/WXDToPONI.py
paws/core/operations/IO/CALIBRATION/__init__.py
paws/core/operations/IO/CSV/CSVToArray.py
paws/core/operations/IO/CSV/CSVToXYData.py
paws/core/operations/IO/CSV/WriteArrayCSV.py
paws/core/operations/IO/CSV/__init__.py
paws/core/operations/IO/IMAGE/FabIOOpen.py
paws/core/operations/IO/IMAGE/FabIOWrite.py
paws/core/operations/IO/IMAGE/LoadTif.py
paws/core/operations/IO/IMAGE/LoadTif_PIL.py
paws/core/operations/IO/IMAGE/__init__.py
paws/core/operations/IO/MISC/ReadNPSynthRecipe.py
paws/core/operations/IO/MISC/__init__.py
paws/core/operations/IO/MODELS/__init__.py
paws/core/operations/IO/MODELS/SAXS/LoadSAXSClassifier.py
paws/core/operations/IO/MODELS/SAXS/__init__.py
paws/core/operations/IO/PIF/CheckDataSet.py
paws/core/operations/IO/PIF/SavePIFAsJSON.py
pypaws-0.7.16.dist-info/DESCRIPTION.rst
pypaws-0.7.16.dist-info/METADATA
pypaws-0.7.16.dist-info/RECORD
pypaws-0.7.16.dist-info/WHEEL
pypaws-0.7.16.dist-info/entry_points.txt
pypaws-0.7.16.dist-info/metadata.json
pypaws-0.7.16.dist-info/top_level.txt
