Metadata-Version: 2.0
Name: pypaws
Version: 0.7.16
Summary: the Platform for Automated Workflows by SSRL
Home-page: https://github.com/slaclab/paws/
Author: Lenson A. Pellouchoud, Amanda Fournier, Ekaterina Tcareva, Ronald Pandolfi, Dinesh Kumar, Fang Ren, Yuriy Kolotovsky, Apurva Mehta, Christopher Tassone
Author-email: paws-developers@slac.stanford.edu
License: BSD
Keywords: data analysis workflow
Platform: UNKNOWN
Classifier: Development Status :: 3 - Alpha
Classifier: License :: OSI Approved :: BSD License
Classifier: Intended Audience :: Science/Research
Classifier: Intended Audience :: Developers
Classifier: Topic :: Scientific/Engineering
Classifier: Programming Language :: Python :: 2.7
Classifier: Programming Language :: Python :: 3.5
Requires-Python: >=2.6
Requires-Dist: pyyaml
